metrics_logger/__init__.py
metrics_logger/decorators.py
metrics_logger-0.1.0.dist-info/METADATA
metrics_logger-0.1.0.dist-info/WHEEL
metrics_logger-0.1.0.dist-info/top_level.txt
metrics_logger-0.1.0.dist-info/RECORD
