Metadata-Version: 2.1
Name: metrics-logger
Version: 0.1.0
Summary: Standardized logging for metrics capture for applications with requirements.
Author-email: John Glorioso <jglorioso@stsci.edu>
Project-URL: source, https://github.com/spacetelescope/metrics_logger
Requires-Python: >=3.9
Requires-Dist: pytest
Provides-Extra: test
Requires-Dist: pytest ; extra == 'test'
Requires-Dist: pytest-cov ; extra == 'test'
